uosclient/__init__.py
uosclient/network.py
uosclient/port.py
uosclient/project.py
uosclient/secgroup.py
uosclient/user.py
uosclient-0.0.13.dist-info/COPYING
uosclient-0.0.13.dist-info/METADATA
uosclient-0.0.13.dist-info/WHEEL
uosclient-0.0.13.dist-info/entry_points.txt
uosclient-0.0.13.dist-info/top_level.txt
uosclient-0.0.13.dist-info/RECORD
