Metadata-Version: 2.1
Name: uosclient
Version: 0.0.13
Summary: Unipart OpenStack client tools
Home-page: https://github.com/unipartdigital/uosclient
Author: Unipart Digital
Author-email: sysadmins@unipart.io
License: GPLv2+
Platform: UNKNOWN
Classifier: Development Status :: 3 - Alpha
Classifier: Environment :: Console
Classifier: Environment :: OpenStack
Classifier: Intended Audience :: System Administrators
Classifier: License :: OSI Approved :: GNU General Public License v2 or later (GPLv2+)
Classifier: Programming Language :: Python :: 3
Classifier: Topic :: System :: Systems Administration
Requires-Python: >=3.7
Requires-Dist: netaddr
Requires-Dist: osc-lib
Requires-Dist: passlib
Requires-Dist: python-designateclient
Requires-Dist: python-openstackclient
